nibeuplink/__init__.py
nibeuplink/__main__.py
nibeuplink/const.py
nibeuplink/exceptions.py
nibeuplink/monitor.py
nibeuplink/py.typed
nibeuplink/session.py
nibeuplink/types.py
nibeuplink/typing.py
nibeuplink/uplink.py
nibeuplink/utils.py
nibeuplink-1.3.0.dist-info/LICENSE.txt
nibeuplink-1.3.0.dist-info/METADATA
nibeuplink-1.3.0.dist-info/WHEEL
nibeuplink-1.3.0.dist-info/entry_points.txt
nibeuplink-1.3.0.dist-info/top_level.txt
nibeuplink-1.3.0.dist-info/RECORD
