Metadata-Version: 2.1
Name: nibeuplink
Version: 1.3.0
Summary: A python wrapper around Nibe Uplink REST API
Home-page: https://github.com/elupus/nibeuplink
Author: Joakim Plate
License: MIT
Platform: UNKNOWN
Classifier: License :: OSI Approved :: MIT License
Classifier: Development Status :: 4 - Beta
Classifier: Environment :: Console
Classifier: Environment :: Plugins
Classifier: Framework :: AsyncIO
Requires-Python: >=3.6
License-File: LICENSE.txt
Requires-Dist: asyncio
Requires-Dist: aiohttp
Requires-Dist: attrs (>18.1)
Requires-Dist: typing-extensions
Provides-Extra: tests
Requires-Dist: pytest (>3.6.4) ; extra == 'tests'
Requires-Dist: pytest-aiohttp ; extra == 'tests'
Requires-Dist: pytest-cov (<2.6) ; extra == 'tests'
Requires-Dist: coveralls ; extra == 'tests'
Requires-Dist: asynctest ; extra == 'tests'
Requires-Dist: aioresponses ; extra == 'tests'
